raidionicsrads/__init__.py
raidionicsrads/__main__.py
raidionicsrads/compute.py
raidionicsrads/Atlases/BrainGrid/Voxels/BG_regions_description.csv
raidionicsrads/Atlases/BrainGrid/Voxels/braingrid_voxels_atlas.nii.gz
raidionicsrads/Atlases/BrainGrid/White_matter_atlas/braingrid_subcortical_structures_description.csv
raidionicsrads/Atlases/BrainGrid/White_matter_atlas/braingrid_subcortical_structures_overall_mask.nii.gz
raidionicsrads/Atlases/BrainGrid/White_matter_atlas/StandAlone/Acoustic_radiation_left.nii.gz
raidionicsrads/Atlases/BrainGrid/White_matter_atlas/StandAlone/Acoustic_radiation_right.nii.gz
raidionicsrads/Atlases/BrainGrid/White_matter_atlas/StandAlone/Anterior_Thalamic_Radiation_left.nii.gz
raidionicsrads/Atlases/BrainGrid/White_matter_atlas/StandAlone/Anterior_Thalamic_Radiation_right.nii.gz
raidionicsrads/Atlases/BrainGrid/White_matter_atlas/StandAlone/Arcuate_Fasciculus_left.nii.gz
raidionicsrads/Atlases/BrainGrid/White_matter_atlas/StandAlone/Arcuate_Fasciculus_right.nii.gz
raidionicsrads/Atlases/BrainGrid/White_matter_atlas/StandAlone/Body_of_corpus_callosum.nii.gz
raidionicsrads/Atlases/BrainGrid/White_matter_atlas/StandAlone/Cingulum_left.nii.gz
raidionicsrads/Atlases/BrainGrid/White_matter_atlas/StandAlone/Cingulum_right.nii.gz
raidionicsrads/Atlases/BrainGrid/White_matter_atlas/StandAlone/Cortico-Spinal_Tract_left.nii.gz
raidionicsrads/Atlases/BrainGrid/White_matter_atlas/StandAlone/Cortico-Spinal_Tract_right.nii.gz
raidionicsrads/Atlases/BrainGrid/White_matter_atlas/StandAlone/External_capsule_left.nii.gz
raidionicsrads/Atlases/BrainGrid/White_matter_atlas/StandAlone/External_capsule_right.nii.gz
raidionicsrads/Atlases/BrainGrid/White_matter_atlas/StandAlone/Fornix_left.nii.gz
raidionicsrads/Atlases/BrainGrid/White_matter_atlas/StandAlone/Fornix_right.nii.gz
raidionicsrads/Atlases/BrainGrid/White_matter_atlas/StandAlone/Frontal_Aslant_Tract_right.nii.gz
raidionicsrads-1.3.2.dist-info/licenses/LICENSE.md
raidionicsrads-1.3.2.dist-info/METADATA
raidionicsrads-1.3.2.dist-info/WHEEL
raidionicsrads-1.3.2.dist-info/entry_points.txt
raidionicsrads-1.3.2.dist-info/top_level.txt
raidionicsrads-1.3.2.dist-info/RECORD
