Metadata-Version: 2.4
Name: raidionicsrads
Version: 1.3.2
Summary: Raidionics reporting and data system backend (RADS)
Author: David Bouget (david.bouget@sintef.no)
License: BSD 2-Clause
Requires-Python: >=3.9
License-File: LICENSE.md
Requires-Dist: raidionicsseg>=1.5.0
Requires-Dist: scikit-learn; platform_system == "Darwin" and platform_machine == "arm64"
Requires-Dist: statsmodels; platform_system == "Darwin" and platform_machine == "arm64"
Requires-Dist: antspyx==0.4.2; platform_system == "Windows" and python_version < "3.10"
Requires-Dist: antspyx==0.6.1; platform_system == "Windows" and python_version >= "3.10"
Requires-Dist: antspyx==0.6.1; platform_system != "Windows" and platform_machine != "arm64"
Dynamic: author
Dynamic: description
Dynamic: description-content-type
Dynamic: license
Dynamic: license-file
Dynamic: requires-dist
Dynamic: requires-python
Dynamic: summary
